1_RTL/4_COMB_LOGIC/2_INTERRUPT/interrupt.v
module interrupt(

i_int_ack,
i_int_address,

o_int_req,
o_int_id

);

input i_int_ack;
input [7:0] i_int_address;

output o_int_req;
output [2:0] o_int_id;

reg [7:0] r_saveAD;
reg [2:0] o_int_id;
reg o_int_req;


always @(*) begin
	o_int_req    = 1'b0         ;          
    	o_int_id     = 3'b000       ;         
    	r_saveAD = i_int_address    ;       
	if(i_int_ack) r_saveAD = 8'b0000_0000;
	else begin

		casex(r_saveAD)
			8'b1xxx_xxxx : begin  o_int_id =3'b111; o_int_req=1; end  	
			8'b01xx_xxxx : begin  o_int_id =3'b110; o_int_req=1; end  	
			8'b001x_xxxx : begin  o_int_id =3'b101; o_int_req=1; end  	
			8'b0001_xxxx : begin  o_int_id =3'b100; o_int_req=1; end  	
			8'b0000_1xxx : begin  o_int_id =3'b011; o_int_req=1; end  	
			8'b0000_01xx : begin  o_int_id =3'b010; o_int_req=1; end  	
			8'b0000_001x : begin  o_int_id =3'b001; o_int_req=1; end  	
			8'b0000_0001 : begin  o_int_id =3'b000; o_int_req=1; end
			default : begin o_int_id =3'b000; o_int_req=0; end   	

		endcase

	end
end 



endmodule

1_RTL/4_COMB_LOGIC/2_INTERRUPT/tb_interrupt.v
module tb_interrupt;

reg [7:0] i_int_address;
reg i_int_ack;

wire [2:0] o_int_id;
wire o_int_req;


interrupt DUT (

.i_int_address(i_int_address),
.i_int_ack(i_int_ack),
.o_int_req(o_int_req),
.o_int_id(o_int_id)
);


initial begin
    $dumpfile("./interrupt.vcd") ;
    $dumpvars(0, tb_interrupt)   ;
end

initial begin

$monitor("Time=%0t | i_int_address=%b | i_int_ack=%b | o_int_id=%b | o_int_req=%b", 
            $time, i_int_address, i_int_ack, o_int_id, o_int_req);

    i_int_address = 8'b0000_000  ; 
    i_int_ack = 1'b0 ;      
                
    // apply stimulus
    #10 i_int_address = 8'b0000_0001  ;  
    #10 i_int_address = 8'b0010_0000  ;  
    #10 i_int_address = 8'b1000_0000  ;  
    #10 i_int_ack   = 1'b1 ;       
    #10 i_int_ack   = 1'b0 ;       
                                            
    #10 i_int_address = 8'b0100_0010;  
    #10 i_int_ack = 1'b1;       
    #10 i_int_ack = 1'b0;
    //                                                                 
     #10 i_int_address = 8'b0000_0000;  
                                                                                
     #20 $finish;             
end

endmodule

1_RTL/4_COMB_LOGIC/2_INTERRUPT/interrupt.vcd
$date
    Jul  1, 2026  02:45:40
$end
$version
    TOOL:	xmsim(64)	22.03-s012
$end
$timescale
    1 ns
$end

$scope module tb_interrupt $end
$var reg       8 !    i_int_address [7:0] $end
$var reg       1 "    i_int_ack $end
$var wire      3 #    o_int_id [2:0] $end
$var wire      1 $    o_int_req  $end

$scope module DUT $end
$var wire      1 %    i_int_ack  $end
$var wire      8 &    i_int_address [7:0] $end
$var reg       1 '    o_int_req $end
$var reg       3 (    o_int_id [2:0] $end
$var reg       8 )    r_saveAD [7:0] $end
$upscope $end

$upscope $end

$enddefinitions $end
$dumpvars
b0 !
0"
b0 #
0$
0%
b0 &
0'
b0 (
b0 )
$end
#10
b1 !
b1 &
b1 )
1'
1$
#20
b100000 !
b100000 &
0'
b100000 )
b101 (
1'
b101 #
#30
b10000000 !
b10000000 &
0'
b0 (
b10000000 )
b111 (
1'
b111 #
#40
1"
1%
0'
b0 (
b0 )
b0 #
0$
#50
0"
0%
b10000000 )
b111 (
1'
1$
b111 #
#60
b1000010 !
b1000010 &
0'
b0 (
b1000010 )
b110 (
1'
b110 #
#70
1"
1%
0'
b0 (
b0 )
b0 #
0$
#80
0"
0%
b1000010 )
b110 (
1'
1$
b110 #
#90
b0 !
b0 &
0'
b0 (
b0 )
b0 #
0$
