1_RTL/4_COMB_LOGIC/3_bcd_to_7seg/bcd_to_7seg.v
module bcd_to_7seg(

i_input,
o_output

);

input [3:0] i_input;
output [7:0] o_output;


reg [6:0] o_output;


always @ (*) begin
	case(i_input)
	4'd0 : o_output =7'b111_1110;
	4'd1 : o_output =7'b011_0000;
	4'd2 : o_output =7'b110_1100;
	4'd3 : o_output =7'b111_1001;
	4'd4 : o_output =7'b011_0011;
	4'd5 : o_output =7'b101_1011;
	4'd6 : o_output =7'b101_1111;
	4'd7 : o_output =7'b111_0000;
	4'd8 : o_output =7'b111_1111;
	4'd9 : o_output =7'b111_0111;
	endcase


end

endmodule

1_RTL/4_COMB_LOGIC/3_bcd_to_7seg/tb_bcd_to_7seg.v


module tb_bcd_to_7seg;

// stimulus signal
reg     [3:0] i_input   ;           
// // monitor signal
wire    [6:0] o_output     ;          
//
// // DUT instantiation
 bcd_to_7seg uut (
     .i_input(i_input),
     .o_output(o_output)
         );

//         // Dumpfile gen
initial begin
$dumpfile("./bcd_to_7seg.vcd"   );
$dumpvars(0, tb_bcd_to_7seg     );
end
//
//                 // apply stimulus
initial begin
//                     // monitoring
	$monitor("Time=%0t | i_bcd Input=%b | Seven Segment  Output=%b", $time, i_input, o_output);
//
//                             // apply stimulus
 	i_input = 4'b0000; #10; 
        i_input = 4'b0001; #10; 
        i_input = 4'b0010; #10; 
        i_input = 4'b0011; #10; 
        i_input = 4'b0100; #10; 
        i_input = 4'b0101; #10; 
        i_input = 4'b0110; #10; 
        i_input = 4'b0111; #10;  
        i_input = 4'b1000; #10;  
        i_input = 4'b1001; #10;  
       $finish ; 
end

endmodule

1_RTL/4_COMB_LOGIC/3_bcd_to_7seg/bcd_to_7seg.vcd
$date
    Jul  1, 2026  19:33:10
$end
$version
    TOOL:	xmsim(64)	22.03-s012
$end
$timescale
    1 ns
$end

$scope module tb_bcd_to_7seg $end
$var reg       4 !    i_input [3:0] $end
$var wire      7 "    o_output [6:0] $end

$scope module uut $end
$var wire      4 #    i_input [3:0] $end
$var reg       7 $    o_output [6:0] $end
$upscope $end

$upscope $end

$enddefinitions $end
$dumpvars
b0 !
b1111110 "
b0 #
b1111110 $
$end
#10
b1 !
b1 #
b110000 $
b110000 "
#20
b10 !
b10 #
b1101100 $
b1101100 "
#30
b11 !
b11 #
b1111001 $
b1111001 "
#40
b100 !
b100 #
b110011 $
b110011 "
#50
b101 !
b101 #
b1011011 $
b1011011 "
#60
b110 !
b110 #
b1011111 $
b1011111 "
#70
b111 !
b111 #
b1110000 $
b1110000 "
#80
b1000 !
b1000 #
b1111111 $
b1111111 "
#90
b1001 !
b1001 #
b1110111 $
b1110111 "
